voice_code.cpython-310-darwin.so
voice_code_resource/1.icns
voice_code_resource/file_dir.py
voice_code_resource/main.py
voice_code_resource/Easy_Code_pics/break.png
voice_code_resource/Easy_Code_pics/continue.png
voice_code_resource/Easy_Code_pics/elif .png
voice_code_resource/Easy_Code_pics/elif2 .png
voice_code_resource/Easy_Code_pics/else.png
voice_code_resource/Easy_Code_pics/else2.png
voice_code_resource/Easy_Code_pics/else3.png
voice_code_resource/Easy_Code_pics/for .png
voice_code_resource/Easy_Code_pics/for .psd
voice_code_resource/Easy_Code_pics/if .png
voice_code_resource/Easy_Code_pics/if .psd
voice_code_resource/Easy_Code_pics/return.png
voice_code_resource/Easy_Code_pics/while .png
voice_code_resource/Easy_Code_res/DroidSansMono-1.ttf
voice_code_resource/Easy_Code_res/completion.txt
voice_code_resource/Easy_Code_res/english_words.txt
voice_code_resource/Easy_Code_res/language.txt
voice_code_resource/Easy_Code_res/tips.txt
voice_code_resource/Easy_Code_res/undefined_names.cpython-310-darwin.so
voice_code_resource/Easy_Code_res/images/alignment.png
voice_code_resource/Easy_Code_res/images/background color.png
voice_code_resource/Easy_Code_res/images/brush.png
voice_code_resource/Easy_Code_res/images/canvas.png
voice_code_resource/Easy_Code_res/images/category.png
voice_code_resource/Easy_Code_res/images/clear.png
voice_code_resource/Easy_Code_res/images/close.png
voice_code_resource/Easy_Code_res/images/code.png
voice_code_resource/Easy_Code_res/images/color.png
voice_code_resource/Easy_Code_res/images/commit.png
voice_code_resource/Easy_Code_res/images/content.png
voice_code_resource/Easy_Code_res/images/copy.png
voice_code_resource/Easy_Code_res/images/down.png
voice_code_resource/Easy_Code_res/images/drawing.png
voice_code_resource/Easy_Code_res/images/export.png
voice_code_resource/Easy_Code_res/images/font.png
voice_code_resource/Easy_Code_res/images/height.png
voice_code_resource/Easy_Code_res/images/move.png
voice_code-0.99.16.dist-info/METADATA
voice_code-0.99.16.dist-info/WHEEL
voice_code-0.99.16.dist-info/entry_points.txt
voice_code-0.99.16.dist-info/top_level.txt
voice_code-0.99.16.dist-info/RECORD
