Metadata-Version: 2.2
Name: voice_code
Version: 0.99.16
Summary: voice_code project
Requires-Dist: cryptography>=42.0.5
Requires-Dist: pyaudio>=0.2.14
Requires-Dist: openai>=1.36.1
Requires-Dist: vosk>=0.3.44
Requires-Dist: numpy>=1.15.4
Requires-Dist: scipy>=1.13.1
Requires-Dist: send2trash>=1.8.2
Requires-Dist: jsonpickle>=1.4.1
Requires-Dist: python-docx>=0.8.10
Requires-Dist: sounddevice>=0.4.1
Requires-Dist: pyqt6>=6.5.2
Requires-Dist: setuptools>=58.1.0
Requires-Dist: voice_code2>=0.0.2
Requires-Dist: beautifulsoup4>=4.12.3
Requires-Dist: metaphone>=0.6
Requires-Dist: qtmodern>=0.2.0
Requires-Dist: pygments>=2.18.0
Requires-Dist: asttokens>=3.0.0
Requires-Dist: networkx>=3.2.1
Requires-Dist: matplotlib>=3.9.0
Requires-Dist: Levenshtein>=0.26.1
Requires-Dist: debugpy>=1.8.11
Requires-Dist: ruff==0.1.6
Requires-Dist: pyttsx3>=2.98
Requires-Dist: requests>=2.32.3
Requires-Dist: plotly>=5.24.1
Requires-Dist: pandas>=2.2.3
Requires-Dist: oss2>=2.19.1
Dynamic: description
Dynamic: description-content-type
Dynamic: requires-dist
Dynamic: summary
